{"crucible_pre":159,"crucible_pre_fast":6,"crucible_pre_msg":7,"crucible_post":190,"crucible_post_fast":3,"crucible_post_msg":5,"p2900_pre":181,"p2900_post":10,"contract_assert":54,"decide_total":260,"total_pre_cites":353,"total_post_cites":208,"total_contract_cites":615,"decide_per_procedure":{"is_non_zero":37,"in_range":63,"all_in_range":0,"aligned_in_range":0,"no_overflow_mul":1,"no_overflow_sum":4,"no_overflow_pow2_shift":0,"is_power_of_two_le":12,"factorization_eq":0,"coprime":0,"intervals_pairwise_disjoint":0,"intervals_cover_unit":0,"tier_replaces":3,"row_subset":0,"fmix_preserves_non_zero":0,"strictly_increasing":0,"weakly_increasing":5,"conjunction":0,"disjunction":0,"implies":15,"positive":7,"non_negative":2,"valid_span":12}}
